route53_ddns/__init__.py
route53_ddns/cli.py
route53_ddns/ip_utilities.py
route53_ddns/route53_interface.py
route53_ddns-0.0.3.dist-info/LICENSE
route53_ddns-0.0.3.dist-info/METADATA
route53_ddns-0.0.3.dist-info/WHEEL
route53_ddns-0.0.3.dist-info/entry_points.txt
route53_ddns-0.0.3.dist-info/top_level.txt
route53_ddns-0.0.3.dist-info/RECORD
