Metadata-Version: 2.1
Name: route53-ddns
Version: 0.0.3
Summary: A simple package that updated an AWS Route53 A record to point to the current IP
Home-page: https://github.com/carlesso/route53-ddns
Author: Enrico Carlesso
Author-email: enricocarlesso@gmail.com
License: UNKNOWN
Project-URL: Bug Tracker, https://github.com/carlesso/route53-ddns/issues
Platform: UNKNOWN
Classifier: Programming Language :: Python :: 3
Classifier: License :: OSI Approved :: MIT License
Classifier: Operating System :: OS Independent
Requires-Python: >=3.6
License-File: LICENSE
Requires-Dist: click
Requires-Dist: boto3
Requires-Dist: requests
Requires-Dist: tenacity
Provides-Extra: test
Requires-Dist: black ; extra == 'test'
Requires-Dist: isort ; extra == 'test'
Requires-Dist: mypy ; extra == 'test'
Requires-Dist: pytest ; extra == 'test'
Requires-Dist: pytest-cov ; extra == 'test'
